yaohu_music_mcp/__init__.py
yaohu_music_mcp-0.1.0.dist-info/METADATA
yaohu_music_mcp-0.1.0.dist-info/WHEEL
yaohu_music_mcp-0.1.0.dist-info/entry_points.txt
yaohu_music_mcp-0.1.0.dist-info/RECORD
