Metadata-Version: 2.4
Name: yaohu-music-mcp
Version: 0.1.0
Summary: Add your description here
Author-email: yshuai <yuanshuai1995@outlook.com>
Requires-Python: >=3.13
Requires-Dist: fastmcp>=2.10.4
Requires-Dist: playsound3>=3.2.4
Requires-Dist: requests>=2.32.4
